<layer>
  <name>SeamapAus_BOUNDARIES_AMP_NETWORK</name>
  <id>LayerInfoImpl--a145589:18952165369:3392</id>
  <type>VECTOR</type>
  <defaultStyle>
    <id>StyleInfoImpl--a145589:18952165369:367b</id>
  </defaultStyle>
  <resource class="featureType">
    <id>FeatureTypeInfoImpl--a145589:18952165369:3391</id>
  </resource>
  <attribution>
    <logoWidth>0</logoWidth>
    <logoHeight>0</logoHeight>
  </attribution>
  <dateCreated>2023-07-14 03:46:36.582 UTC</dateCreated>
  <dateModified>2023-07-14 04:08:23.945 UTC</dateModified>
</layer>