<layer>
  <name>NESP_D3_Tier1_localscale_reef_full</name>
  <id>LayerInfoImpl-2ae9b1f8:180c2915d17:-7ffe</id>
  <type>VECTOR</type>
  <defaultStyle>
    <id>StyleInfoImpl--3ea8dad8:157bb635de2:2db3</id>
  </defaultStyle>
  <resource class="featureType">
    <id>FeatureTypeInfoImpl-2ae9b1f8:180c2915d17:-7fff</id>
  </resource>
  <queryable>true</queryable>
  <attribution>
    <logoWidth>0</logoWidth>
    <logoHeight>0</logoHeight>
  </attribution>
  <dateModified>2026-02-27 02:54:58.258 UTC</dateModified>
</layer>