<wmtsStore>
  <id>WMTSStoreInfoImpl-50e6ef9f:17cca7ae7c7:52b8</id>
  <name>GBR10_GBRMP_benthic_habitat</name>
  <type>WMTS</type>
  <enabled>true</enabled>
  <workspace>
    <id>WorkspaceInfoImpl-513dc49c:1562676d393:-568a</id>
  </workspace>
  <metadata>
    <entry key="useConnectionPooling">true</entry>
  </metadata>
  <__default>false</__default>
  <capabilitiesURL>https://tiles.arcgis.com/tiles/ll1QQ2mI4WMXIXdm/arcgis/rest/services/BenthicLayerV2/MapServer/WMTS</capabilitiesURL>
  <user>admin</user>
  <password>crypt1:jKri8nWu+TsmXJVCGpT2RgQhA/gSz+bF</password>
  <maxConnections>6</maxConnections>
  <readTimeout>60</readTimeout>
  <connectTimeout>30</connectTimeout>
</wmtsStore>