<layer>
  <name>Glyphis_glyphis_suitable_habitat_thresholded</name>
  <id>LayerInfoImpl--63c24095:18de9372c64:-7d80</id>
  <type>RASTER</type>
  <defaultStyle>
    <id>StyleInfoImpl--63c24095:18de4890c06:3db8</id>
  </defaultStyle>
  <resource class="coverage">
    <id>CoverageInfoImpl--63c24095:18de9372c64:-7d81</id>
  </resource>
  <attribution>
    <logoWidth>0</logoWidth>
    <logoHeight>0</logoHeight>
  </attribution>
  <defaultWMSInterpolationMethod>Nearest</defaultWMSInterpolationMethod>
  <dateCreated>2024-02-27 07:07:31.281 UTC</dateCreated>
  <dateModified>2024-02-27 07:21:51.278 UTC</dateModified>
</layer>